gsdesign/__init__.py
gsdesign/integration.py
gsdesign-0.1.4.dist-info/METADATA
gsdesign-0.1.4.dist-info/WHEEL
gsdesign-0.1.4.dist-info/licenses/LICENSE
gsdesign-0.1.4.dist-info/RECORD
