Metadata-Version: 2.4
Name: gsdesign
Version: 0.1.4
Summary: Group sequential design
Project-URL: Repository, https://github.com/nanxstats/gsdesign-python
Project-URL: Issues, https://github.com/nanxstats/gsdesign-python/issues
Project-URL: Changelog, https://github.com/nanxstats/gsdesign-python/blob/main/CHANGELOG.md
Author-email: Nan Xiao <me@nanx.me>
License-File: LICENSE
Classifier: Development Status :: 3 - Alpha
Classifier: Intended Audience :: Science/Research
Classifier: License :: OSI Approved :: MIT License
Classifier: Operating System :: OS Independent
Classifier: Programming Language :: Python :: 3
Classifier: Programming Language :: Python :: 3.10
Classifier: Programming Language :: Python :: 3.11
Classifier: Programming Language :: Python :: 3.12
Classifier: Programming Language :: Python :: 3.13
Classifier: Programming Language :: Python :: 3.14
Classifier: Topic :: Scientific/Engineering :: Mathematics
Classifier: Typing :: Typed
Requires-Python: >=3.10
Requires-Dist: numpy>=2.0.0
